spider/__init__.py
spider/__main__.py
spider/proxy.py
rainbowspiderproxy-1.0.0.dist-info/METADATA
rainbowspiderproxy-1.0.0.dist-info/WHEEL
rainbowspiderproxy-1.0.0.dist-info/top_level.txt
rainbowspiderproxy-1.0.0.dist-info/RECORD
